epsonprinter_pkg/__init__.py
epsonprinter_pkg/epsonprinterapi.py
epsonprinter_api-1.0.1.dist-info/LICENSE
epsonprinter_api-1.0.1.dist-info/METADATA
epsonprinter_api-1.0.1.dist-info/WHEEL
epsonprinter_api-1.0.1.dist-info/top_level.txt
epsonprinter_api-1.0.1.dist-info/RECORD
