Metadata-Version: 2.1
Name: epsonprinter-api
Version: 1.0.1
Summary: Communication package for Epson Workforce printer
Home-page: https://github.com/cociweb/epsonprinter-api
Author: cociweb
Author-email: cociweb <author@example.com>
Project-URL: Homepage, https://github.com/cociweb/epsonprinter-api
Project-URL: Issues, https://github.com/cociweb/epsonprinter-api/issues
Classifier: Programming Language :: Python :: 3
Classifier: License :: OSI Approved :: MIT License
Classifier: Operating System :: OS Independent
Requires-Python: >=3.6
License-File: LICENSE
